hopfield4py/__init__.py
hopfield4py/diluted.py
hopfield4py/hopfield.py
hopfield4py/hopfield_helper.py
hopfield4py-0.1.0.dist-info/LICENSE
hopfield4py-0.1.0.dist-info/METADATA
hopfield4py-0.1.0.dist-info/WHEEL
hopfield4py-0.1.0.dist-info/top_level.txt
hopfield4py-0.1.0.dist-info/RECORD
