Metadata-Version: 2.1
Name: hopfield4py
Version: 0.1.0
Summary: Package to run Hopfield model.
Home-page: https://bitbucket.org/fvalle01/hopfield4py
Author: Filippo Valle
Author-email: filippo.valle@unito.it
License: UNKNOWN
Platform: UNKNOWN
Classifier: Programming Language :: Python :: 3
Classifier: License :: OSI Approved :: MIT License
Classifier: Operating System :: OS Independent
Requires-Python: >=3.6
Requires-Dist: tensorflow
